patentmodels/__init__.py
patentmodels/basemodels.py
patentmodels/claim.py
patentmodels/claimset.py
patentmodels/classification.py
patentmodels/patentcorpus.py
patentmodels/specification.py
patentmodels/lib/__init__.py
patentmodels/lib/utils.py
patentmodels/lib/utils_claim.py
patentmodels/lib/utils_claimset.py
patentmodels-0.0.5.dist-info/DESCRIPTION.rst
patentmodels-0.0.5.dist-info/METADATA
patentmodels-0.0.5.dist-info/RECORD
patentmodels-0.0.5.dist-info/WHEEL
patentmodels-0.0.5.dist-info/metadata.json
patentmodels-0.0.5.dist-info/top_level.txt
